astar_wxsdk/__init__.py
astar_wxsdk/common.py
astar_wxsdk/component.py
astar_wxsdk/events.py
astar_wxsdk/fields.py
astar_wxsdk/messages.py
astar_wxsdk/oauth.py
astar_wxsdk/parser.py
astar_wxsdk/util.py
astar_wxsdk/client/__init__.py
astar_wxsdk/client/_client.py
astar_wxsdk/client/base.py
astar_wxsdk/client/api/__init__.py
astar_wxsdk/client/api/base.py
astar_wxsdk/client/api/card.py
astar_wxsdk/client/api/customservice.py
astar_wxsdk/client/api/datacube.py
astar_wxsdk/client/api/device.py
astar_wxsdk/client/api/group.py
astar_wxsdk/client/api/invoice.py
astar_wxsdk/client/api/jsapi.py
astar_wxsdk/client/api/marketing.py
astar_wxsdk/client/api/material.py
astar_wxsdk/client/api/media.py
astar_wxsdk/client/api/menu.py
astar_wxsdk/client/api/message.py
astar_wxsdk/client/api/misc.py
astar_wxsdk/client/api/poi.py
astar_wxsdk/client/api/qrcode.py
astar_wxsdk/client/api/scan.py
astar_wxsdk/client/api/semantic.py
astar_wxsdk/client/api/shakearound.py
astar_wxsdk/client/api/tag.py
astar_wxsdk/client/api/template.py
astar_wxsdk/client/api/user.py
astar_wxsdk/client/api/wifi.py
astar_wxsdk/client/api/wxa.py
astar_wxsdk/client/api/merchant/__init__.py
astar_wxsdk/client/api/merchant/category.py
astar_wxsdk/client/api/merchant/common.py
astar_wxsdk/client/api/merchant/express.py
astar_wxsdk/client/api/merchant/group.py
astar_wxsdk/client/api/merchant/order.py
astar_wxsdk/client/api/merchant/shelf.py
astar_wxsdk/client/api/merchant/stock.py
astar_wxsdk/exceptions/__init__.py
astar_wxsdk/exceptions/_exceptions.py
astar_wxsdk/pay/__init__.py
astar_wxsdk/pay/_pay.py
astar_wxsdk/pay/base.py
astar_wxsdk/pay/utils.py
astar_wxsdk/pay/api/__init__.py
astar_wxsdk/pay/api/coupon.py
astar_wxsdk/pay/api/jsapi.py
astar_wxsdk/pay/api/micropay.py
astar_wxsdk/pay/api/order.py
astar_wxsdk/pay/api/redpack.py
astar_wxsdk/pay/api/refund.py
astar_wxsdk/pay/api/tools.py
astar_wxsdk/pay/api/transfer.py
astar_wxsdk/pay/api/withhold.py
astar_wxsdk/replies/__init__.py
astar_wxsdk/replies/_replies.py
astar_wxsdk-0.0.1.dist-info/LICENSE
astar_wxsdk-0.0.1.dist-info/METADATA
astar_wxsdk-0.0.1.dist-info/WHEEL
astar_wxsdk-0.0.1.dist-info/top_level.txt
astar_wxsdk-0.0.1.dist-info/RECORD
